cx_tool/__init__.py
cx_tool/cli.py
cx_tool/config.py
cx_tool/misc.py
cx_tool/plugin/__init__.py
cx_tool/plugin/bottle.py
cx_tool/plugin/completions.py
cx_tool/plugin/context.py
cx_tool/plugin/deps.py
cx_tool/plugin/dxvk.py
cx_tool/plugin/fastmath.py
cx_tool/plugin/linux.py
cx_tool/plugin/mac.py
cx_tool/plugin/plist.py
cx_tool/plugin/plugin.py
cx_tool/plugin/reset.py
cx_tool/plugin/steam.py
cx_tool/plugin/ue4.py
cx_tool/plugin/wine.py
cx_tool-0.1.0.39.dist-info/LICENSE
cx_tool-0.1.0.39.dist-info/METADATA
cx_tool-0.1.0.39.dist-info/WHEEL
cx_tool-0.1.0.39.dist-info/entry_points.txt
cx_tool-0.1.0.39.dist-info/RECORD
