Metadata-Version: 2.1
Name: cx-tool
Version: 0.1.0.39
Summary: Crossover utility tool
License: MIT
Author: Yurzs
Author-email: me@yurzs.dev
Requires-Python: >=3.10
Classifier: License :: OSI Approved :: MIT License
Classifier: Programming Language :: Python :: 3
Classifier: Programming Language :: Python :: 3.10
Classifier: Programming Language :: Python :: 3.11
Classifier: Programming Language :: Python :: 3.12
Requires-Dist: click (>=8.1.7,<9.0.0)
Requires-Dist: plumbum (>=1.8.3,<2.0.0)
Requires-Dist: pydantic (>=2.9.2,<3.0.0)
Requires-Dist: pytz (>=2024.2,<2025.0)
Requires-Dist: rich (>=13.8.1,<14.0.0)
Requires-Dist: typing-extensions (>=4.12.2,<5.0.0)
Requires-Dist: vdf (>=3.4,<4.0)
